timezonefinder-7.0.2.data/data/DATA_LICENSE
timezonefinder-7.0.2.dist-info/entry_points.txt
timezonefinder-7.0.2.dist-info/METADATA
timezonefinder-7.0.2.dist-info/RECORD
timezonefinder-7.0.2.dist-info/top_level.txt
timezonefinder-7.0.2.dist-info/WHEEL
timezonefinder-7.0.2.dist-info/licenses/LICENSE
timezonefinder/__init__.py
timezonefinder/utils_numba.py
timezonefinder/configs.py
timezonefinder/np_binary_helpers.py
timezonefinder/polygon_array.py
timezonefinder/command_line.py
timezonefinder/global_functions.py
timezonefinder/inside_polygon_ext.abi3.so
timezonefinder/py.typed
timezonefinder/utils.py
timezonefinder/build.py
timezonefinder/utils_clang.py
timezonefinder/zone_names.py
timezonefinder/timezonefinder.py
timezonefinder/_numba_replacements.py
timezonefinder/coord_accessors.py
timezonefinder/flatbuf/__init__.py
timezonefinder/flatbuf/shortcut_utils.py
timezonefinder/flatbuf/ShortcutEntry.py
timezonefinder/flatbuf/ShortcutCollection.py
timezonefinder/flatbuf/shortcut_schema.fbs
timezonefinder/flatbuf/polygon_utils.py
timezonefinder/flatbuf/Polygon.py
timezonefinder/flatbuf/polygon_schema.fbs
timezonefinder/flatbuf/PolygonCollection.py
timezonefinder/inside_poly_extension/inside_polygon_int.h
timezonefinder/inside_poly_extension/inside_polygon_int.c
timezonefinder/data/hole_registry.json
timezonefinder/data/zone_ids.npy
timezonefinder/data/shortcuts.fbs
timezonefinder/data/timezone_names.txt
timezonefinder/data/zone_positions.npy
timezonefinder/data/boundaries/coordinates.fbs
timezonefinder/data/boundaries/xmin.npy
timezonefinder/data/boundaries/ymax.npy
timezonefinder/data/boundaries/ymin.npy
timezonefinder/data/boundaries/xmax.npy
timezonefinder/data/holes/coordinates.fbs
timezonefinder/data/holes/xmin.npy
timezonefinder/data/holes/ymax.npy
timezonefinder/data/holes/ymin.npy
timezonefinder/data/holes/xmax.npy
