Metadata-Version: 2.4
Name: timezonefinder
Version: 7.0.2
Summary: python package for finding the timezone of any point on earth (coordinates) offline
Author-email: jannikmi <github@michelfe.it>
License: The MIT License (MIT)
Project-URL: homepage, https://timezonefinder.michelfe.it/gui
Project-URL: repository, https://github.com/jannikmi/timezonefinder
Project-URL: documentation, https://timezonefinder.readthedocs.io/en/latest/
Keywords: timezone,coordinates,latitude,longitude,location,offline,polygon
Classifier: Development Status :: 5 - Production/Stable
Classifier: Intended Audience :: Developers
Classifier: Intended Audience :: Information Technology
Classifier: Natural Language :: English
Classifier: Operating System :: OS Independent
Classifier: Topic :: Software Development :: Localization
Classifier: Programming Language :: Python :: 3.9
Classifier: Programming Language :: Python :: 3.10
Classifier: Programming Language :: Python :: 3.11
Classifier: Programming Language :: Python :: 3.12
Classifier: Programming Language :: Python :: 3.13
Requires-Python: <4,>=3.9
License-File: LICENSE
Requires-Dist: numpy<3,>=1.23; python_version >= "3.9"
Requires-Dist: h3>4
Requires-Dist: cffi<2,>=1.15.1
Requires-Dist: flatbuffers>=25.2.10
Dynamic: license-file
